command_eml_accept_subscription_mailman_plugin/__init__.py
command_eml_accept_subscription_mailman_plugin/commands/__init__.py
command_eml_accept_subscription_mailman_plugin/commands/eml_accept.py
command_eml_accept_subscription_mailman_plugin-1.0.1.dist-info/LICENSE
command_eml_accept_subscription_mailman_plugin-1.0.1.dist-info/METADATA
command_eml_accept_subscription_mailman_plugin-1.0.1.dist-info/WHEEL
command_eml_accept_subscription_mailman_plugin-1.0.1.dist-info/top_level.txt
command_eml_accept_subscription_mailman_plugin-1.0.1.dist-info/RECORD
